teext/__init__.py
teext/constraints.py
teext/lib.cpython-310-x86_64-linux-gnu.so
teext/lib.py
teext/lib.pyi
teext/lib__mypyc.cpython-310-x86_64-linux-gnu.so
teext/optional.py
teext/py.typed
teext/result.py
teext-0.1.9.dist-info/METADATA
teext-0.1.9.dist-info/WHEEL
teext-0.1.9.dist-info/licenses/LICENSE
teext-0.1.9.dist-info/RECORD
