Metadata-Version: 2.1
Name: teext
Version: 0.1.9
Summary: Typing extensions extensions
Project-URL: Homepage, https://github.com/wearepal/teext
Author-email: Thomas MK <tmke@posteo.net>
License-File: LICENSE
Keywords: python,typing
Classifier: License :: OSI Approved :: Apache Software License
Classifier: Operating System :: OS Independent
Classifier: Programming Language :: Python :: 3.8
Classifier: Programming Language :: Python :: 3.9
Classifier: Programming Language :: Python :: 3.10
Classifier: Typing :: Typed
Requires-Python: >=3.8
Requires-Dist: typing-extensions>=4.4.0
